setup.cfg
setup.py
smrzr/__init__.py
smrzr/__main__.py
smrzr/better_sentences.py
smrzr/classy_summarizer.py
smrzr/cli.py
smrzr/core.py
smrzr/exceptions.py
smrzr/formatters.py
smrzr/ui.py
smrzr/utilities.py
smrzr.egg-info/PKG-INFO
smrzr.egg-info/SOURCES.txt
smrzr.egg-info/dependency_links.txt
smrzr.egg-info/top_level.txt