Metadata-Version: 1.1
Name: smrzr
Version: 0.1
Summary: Extracts key points from news articles
Home-page: https://github.com/lekhakpadmanabh/Summarizer
Author: Pamdanabh
Author-email: UNKNOWN
License: Apache
Download-URL: https://github.com/lekhakpadmanabh/Summarizer/tarball/0.1
Platform: UNKNOWN
